{"data":{"site":{"siteMetadata":{"title":"Trafikito - monitor output of any command","author":"Lukas Liesis"}},"markdownRemark":{"id":"ec08b990-7b9b-587c-947d-e3dea9c3c1c7","excerpt":"","html":"<p>\n    All data sources are visible in the settings of the server.\n</p>\n<!--more-->\n<ol>\n    <li>Click the <strong>menu</strong> icon on the top left</li>\n    <li>Go to <strong>Dashboard</strong></li>\n    <li>Click <strong>Open</strong> next to the server name you want to edit</li>\n    <li>Click <strong>Settings</strong> on the top right</li>\n    <li>Click <strong>Show</strong> next to <strong>Data sources</strong></li>\n</ol>\n<p>\n    Here you can see the list of all data sources and variables defined inside them. Click on any item to open full\n    details. You can change the data source name, command, data splitting to table options, variables, and variable\n    display settings.\n</p>","frontmatter":{"title":"How to see data sources?","uri":"how-to-see-data-sources","tags":["data sources"]}}},"pageContext":{"uri":"how-to-see-data-sources","previous":{"frontmatter":{"title":"What are chips in the data source list?","uri":"what-are-chips-in-the-data-source-list","tags":["data sources"]}},"next":{"frontmatter":{"title":"How to monitor a single number from the output of command?","uri":"how-to-monitor-a-single-number-from-the-output-of-command","tags":["data sources"]}}}}