{"data":{"site":{"siteMetadata":{"title":"Trafikito - monitor output of any command","author":"Lukas Liesis"}},"markdownRemark":{"id":"77f69fd8-b13a-5f4f-97cd-1064d954a357","excerpt":"","html":"<p>\n    If your role is an “owner” or “admin” you can disable the login of any current user in a workspace. Just use the\n    switch next to the email of the member. A grey color means a user is not able to login. Follow these steps to do it:\n</p>\n<!--more-->\n<ol>\n    <li>\n        Open the main menu on the top left [menu icon]\n    </li>\n    <li>\n        Select <strong>Dashboard</strong>\n    </li>\n    <li>\n        On top of the servers list, you can see the name of the selected workspace. Click it to open more details\n    </li>\n    <li>\n        On the top select <strong>Members</strong> tab\n    </li>\n    <li>\n        On the member’s list find the email for the member you want to disable; login and use the switch next to it\n    </li>\n</ol>","frontmatter":{"title":"How to remove a member from the workspace?","uri":"how-to-remove-a-member-from-the-workspace","tags":["workspace"]}}},"pageContext":{"uri":"how-to-remove-a-member-from-the-workspace","previous":{"frontmatter":{"title":"How to remove a workspace?","uri":"how-to-remove-a-workspace","tags":["workspace"]}},"next":{"frontmatter":{"title":"How to quickly earn personal discounts?","uri":"how-to-quickly-earn-personal-discounts","tags":["workspace"]}}}}